example_pkg/__init__.py
example_pkg/calculate.py
example_pkg/demo.py
example_pkg_PANDASTEST_01/__init__.py
example_pkg_PANDASTEST_01/calculate.py
example_pkg_PANDASTEST_01-0.0.1.dist-info/LICENSE
example_pkg_PANDASTEST_01-0.0.1.dist-info/METADATA
example_pkg_PANDASTEST_01-0.0.1.dist-info/WHEEL
example_pkg_PANDASTEST_01-0.0.1.dist-info/top_level.txt
example_pkg_PANDASTEST_01-0.0.1.dist-info/RECORD
